[
  {
    "Rank": 1,
    "Time Spent (seconds)": 7599,
    "Number of People": 1,
    "Category": "Design & Composition"
  },
  {
    "Rank": 2,
    "Time Spent (seconds)": 3927,
    "Number of People": 1,
    "Category": "Software Development"
  },
  {
    "Rank": 3,
    "Time Spent (seconds)": 3396,
    "Number of People": 1,
    "Category": "Business"
  },
  {
    "Rank": 4,
    "Time Spent (seconds)": 1448,
    "Number of People": 1,
    "Category": "Uncategorized"
  },
  {
    "Rank": 5,
    "Time Spent (seconds)": 1447,
    "Number of People": 1,
    "Category": "Communication & Scheduling"
  },
  {
    "Rank": 6,
    "Time Spent (seconds)": 651,
    "Number of People": 1,
    "Category": "Utilities"
  },
  {
    "Rank": 7,
    "Time Spent (seconds)": 632,
    "Number of People": 1,
    "Category": "Entertainment"
  },
  {
    "Rank": 8,
    "Time Spent (seconds)": 597,
    "Number of People": 1,
    "Category": "Reference & Learning"
  }
]