{
  "1": {},
  "2": {},
  "3": {},
  "4": {},
  "5": {},
  "6": {
    "Design & Composition": 17723,
    "Business": 6822,
    "Communication & Scheduling": 5459,
    "News & Opinion": 871,
    "Software Development": 1149,
    "Utilities": 674,
    "Entertainment": 730,
    "Reference & Learning": 485,
    "Shopping": 10,
    "Uncategorized": 653
  },
  "7": {
    "Communication & Scheduling": 24458,
    "Design & Composition": 62942,
    "Software Development": 19289,
    "Business": 9708,
    "Utilities": 5104,
    "Shopping": 1768,
    "Reference & Learning": 6824,
    "News & Opinion": 1719,
    "Uncategorized": 2634,
    "Entertainment": 1599,
    "Social Networking": 255
  },
  "8": {},
  "9": {},
  "10": {},
  "11": {},
  "12": {}
}