{
  "1": {
    "Design & Composition": 194768,
    "Business": 94493,
    "Entertainment": 11793,
    "Communication & Scheduling": 80720,
    "Utilities": 25613,
    "Software Development": 48768,
    "Reference & Learning": 18013,
    "News & Opinion": 6172,
    "Uncategorized": 15212,
    "Social Networking": 3536,
    "Shopping": 647
  },
  "2": {
    "Software Development": 55018,
    "Communication & Scheduling": 82795,
    "Business": 50516,
    "Design & Composition": 154293,
    "Utilities": 15378,
    "Uncategorized": 17122,
    "Reference & Learning": 17818,
    "Entertainment": 7689,
    "News & Opinion": 4186,
    "Shopping": 1761,
    "Social Networking": 2037
  },
  "3": {},
  "4": {},
  "5": {},
  "6": {},
  "7": {},
  "8": {},
  "9": {},
  "10": {},
  "11": {},
  "12": {}
}