[
  {
    "summary_date": "2021-10-14",
    "period_id": 0,
    "is_longest": 1,
    "timezone": -420,
    "bedtime_end": "2021-10-15T08:43:01-07:00",
    "bedtime_start": "2021-10-14T22:55:01-07:00",
    "breath_average": 13.875,
    "duration": 35280,
    "total": 30840,
    "awake": 4440,
    "rem": 6720,
    "deep": 4410,
    "light": 19710,
    "midpoint_time": 17640,
    "efficiency": 87,
    "restless": 31,
    "onset_latency": 720,
    "hr_5min": [
      0,
      0,
      56,
      56,
      57,
      57,
      58,
      59,
      59,
      59,
      61,
      62,
      63,
      64,
      65,
      64,
      60,
      59,
      58,
      58,
      58,
      59,
      56,
      57,
      58,
      58,
      58,
      58,
      58,
      56,
      58,
      57,
      58,
      57,
      56,
      54,
      54,
      54,
      55,
      57,
      57,
      57,
      56,
      56,
      52,
      51,
      51,
      51,
      53,
      53,
      53,
      53,
      53,
      53,
      50,
      49,
      49,
      48,
      50,
      51,
      51,
      49,
      50,
      51,
      52,
      51,
      52,
      50,
      48,
      48,
      48,
      47,
      47,
      47,
      45,
      48,
      47,
      47,
      47,
      49,
      48,
      48,
      49,
      47,
      46,
      47,
      48,
      49,
      49,
      48,
      46,
      46,
      47,
      46,
      43,
      44,
      43,
      44,
      43,
      43,
      46,
      45,
      45,
      45,
      45,
      44,
      45,
      45,
      45,
      46,
      46,
      48,
      45,
      45,
      48,
      48,
      48,
      0
    ],
    "hypnogram_5min": "4411111112311114423222421121124212222222333332222233332222222222333222322222332222222233332223222222222222222334424444",
    "rmssd": 24,
    "rmssd_5min": [
      0,
      0,
      20,
      19,
      18,
      18,
      13,
      10,
      12,
      8,
      8,
      11,
      10,
      10,
      9,
      13,
      12,
      10,
      12,
      11,
      11,
      12,
      12,
      12,
      14,
      13,
      11,
      11,
      11,
      15,
      12,
      10,
      10,
      11,
      10,
      13,
      11,
      12,
      12,
      9,
      11,
      12,
      17,
      13,
      15,
      15,
      16,
      18,
      15,
      13,
      14,
      15,
      12,
      12,
      16,
      16,
      16,
      28,
      22,
      16,
      17,
      20,
      18,
      27,
      20,
      20,
      27,
      22,
      48,
      20,
      33,
      49,
      33,
      43,
      68,
      31,
      29,
      25,
      35,
      25,
      26,
      22,
      26,
      27,
      31,
      23,
      19,
      19,
      17,
      33,
      56,
      58,
      37,
      33,
      69,
      52,
      41,
      35,
      60,
      42,
      33,
      22,
      22,
      27,
      21,
      38,
      32,
      36,
      42,
      28,
      55,
      38,
      32,
      38,
      19,
      23,
      34,
      0
    ],
    "score": 89,
    "score_alignment": 75,
    "score_deep": 88,
    "score_disturbances": 74,
    "score_efficiency": 88,
    "score_latency": 91,
    "score_rem": 96,
    "score_total": 97,
    "temperature_deviation": 0.27,
    "temperature_trend_deviation": 0.04,
    "bedtime_start_delta": -3899,
    "bedtime_end_delta": 31381,
    "midpoint_at_delta": 13741,
    "temperature_delta": 0.27,
    "hr_lowest": 43,
    "hr_average": 51.6
  }
]