{
  "1": {
    "Audio Editing": 23050,
    "General Entertainment": 6442,
    "Intelligence": 6544,
    "Email": 20419,
    "General Utilities": 11629,
    "General Software Development": 17532,
    "Writing": 39027,
    "Project Management": 17222,
    "Search": 4194,
    "Browsers": 2133,
    "General Business": 10883,
    "Data Modeling & Analysis": 8759,
    "Marketing": 6250,
    "Editing & IDEs": 1562,
    "Sales": 3876,
    "Calendars": 3034,
    "Internet Utilities": 410,
    "General Reference & Learning": 4329,
    "General News & Opinion": 3496,
    "Presentation": 14556,
    "General Communication & Scheduling": 465,
    "Instant Message": 2850,
    "Uncategorized": 10476,
    "Meetings": 7201,
    "General Design & Composition": 15484,
    "Health & Medicine": 2009,
    "Professional Networking": 1277,
    "Engineering & Technology": 260,
    "Voice Chat": 212,
    "Music": 40,
    "Business & Finance": 54,
    "Systems Operations": 12,
    "Maps & Regional": 2,
    "Video": 2444,
    "Comedy": 1,
    "General Social Networking": 194,
    "General Shopping": 92,
    "Graphic Design": 9,
    "Science & Technology": 485,
    "Sports": 90,
    "Accounting": 125,
    "Entertainment": 71,
    "File Sharing": 137,
    "Operations": 11,
    "Games": 57
  },
  "2": {},
  "3": {},
  "4": {},
  "5": {},
  "6": {},
  "7": {},
  "8": {},
  "9": {},
  "10": {},
  "11": {},
  "12": {}
}