{
  "1": {},
  "2": {},
  "3": {},
  "4": {
    "General Software Development": 2421,
    "General News & Opinion": 1146,
    "Project Management": 1059,
    "Meetings": 1040,
    "Email": 889,
    "Editing & IDEs": 303,
    "General Utilities": 279,
    "Systems Operations": 207,
    "Travel & Outdoors": 167,
    "Browsers": 165,
    "Intelligence": 141,
    "Instant Message": 132,
    "Search": 114,
    "General Communication & Scheduling": 91,
    "Writing": 76,
    "General Design & Composition": 68,
    "Accounting": 52,
    "Games": 48,
    "Uncategorized": 40,
    "General Reference & Learning": 30,
    "Engineering & Technology": 28,
    "Calendars": 27,
    "Professional Networking": 15,
    "General Entertainment": 5
  },
  "5": {
    "Project Management": 3837,
    "Meetings": 3264,
    "General Design & Composition": 2731,
    "Email": 2636,
    "General Software Development": 2461,
    "Writing": 1815,
    "General Business": 1326,
    "Presentation": 1135,
    "General Utilities": 960,
    "Uncategorized": 914,
    "Intelligence": 597,
    "General News & Opinion": 566,
    "Instant Message": 511,
    "Calendars": 500,
    "Browsers": 453,
    "Editing & IDEs": 414,
    "Professional Networking": 359,
    "Science & Technology": 279,
    "General Entertainment": 267,
    "General Communication & Scheduling": 217,
    "Search": 177,
    "Systems Operations": 155,
    "Engineering & Technology": 147,
    "Video": 77,
    "General Reference & Learning": 72,
    "Voice Chat": 15,
    "General Shopping": 4
  },
  "6": {
    "General Software Development": 4830,
    "General Design & Composition": 2417,
    "Writing": 2246,
    "Meetings": 1888,
    "Email": 1496,
    "Project Management": 1289,
    "Professional Networking": 1023,
    "Systems Operations": 898,
    "General News & Opinion": 846,
    "Intelligence": 406,
    "General Utilities": 365,
    "General Reference & Learning": 337,
    "Calendars": 310,
    "Uncategorized": 294,
    "Editing & IDEs": 286,
    "Search": 260,
    "General Business": 252,
    "Browsers": 164,
    "Presentation": 142,
    "General Shopping": 75,
    "Sports": 55,
    "General Entertainment": 25,
    "Graphic Design": 24,
    "Instant Message": 15,
    "Engineering & Technology": 7,
    "Anti-Virus & Spyware": 2
  },
  "7": {
    "Meetings": 4532,
    "Email": 2946,
    "Writing": 2562,
    "General Entertainment": 1359,
    "Project Management": 1312,
    "General Utilities": 1113,
    "Search": 1034,
    "Instant Message": 931,
    "Uncategorized": 894,
    "General Reference & Learning": 582,
    "Intelligence": 510,
    "Professional Networking": 479,
    "General Business": 462,
    "Calendars": 350,
    "General Design & Composition": 198,
    "Browsers": 157,
    "General News & Opinion": 143,
    "Systems Operations": 139,
    "General Software Development": 118,
    "General Communication & Scheduling": 116,
    "Engineering & Technology": 101,
    "Health & Medicine": 88,
    "Marketing": 85,
    "Data Modeling & Analysis": 84,
    "Editing & IDEs": 79,
    "Administration": 40,
    "General Shopping": 11,
    "Internet Utilities": 6,
    "Operations": 4
  },
  "8": {
    "Email": 8025,
    "Writing": 3752,
    "Project Management": 1546,
    "Intelligence": 997,
    "Instant Message": 597,
    "Uncategorized": 379,
    "General Reference & Learning": 377,
    "General News & Opinion": 353,
    "General Software Development": 301,
    "Professional Networking": 194,
    "Editing & IDEs": 187,
    "Browsers": 150,
    "Calendars": 148,
    "Search": 110,
    "General Utilities": 102,
    "General Entertainment": 74,
    "Engineering & Technology": 64,
    "Meetings": 37,
    "Voice Chat": 31,
    "General Business": 3
  },
  "9": {
    "Audio Editing": 1256,
    "Email": 1231,
    "Intelligence": 244,
    "Project Management": 202,
    "General Utilities": 127,
    "Uncategorized": 66,
    "Browsers": 32,
    "General Shopping": 25,
    "General Communication & Scheduling": 18,
    "Systems Operations": 14,
    "Instant Message": 12,
    "Marketing": 10,
    "General Software Development": 10,
    "Search": 3
  },
  "10": {
    "Writing": 3527,
    "Project Management": 2057,
    "General Business": 1323,
    "Email": 1267,
    "Uncategorized": 782,
    "Audio Editing": 698,
    "General Software Development": 677,
    "General Utilities": 664,
    "Intelligence": 525,
    "Data Modeling & Analysis": 224,
    "Search": 214,
    "Marketing": 182,
    "Browsers": 180,
    "Presentation": 162,
    "General Entertainment": 154,
    "Editing & IDEs": 125,
    "General Reference & Learning": 64,
    "Calendars": 64,
    "General Communication & Scheduling": 60,
    "General News & Opinion": 13,
    "Video": 2,
    "Voice Chat": 1
  },
  "11": {
    "Meetings": 2532,
    "Writing": 2158,
    "Uncategorized": 1542,
    "Presentation": 1235,
    "Email": 611,
    "Health & Medicine": 601,
    "General Business": 521,
    "General Utilities": 471,
    "Intelligence": 308,
    "Calendars": 233,
    "General Entertainment": 200,
    "General Reference & Learning": 189,
    "Search": 180,
    "Sports": 170,
    "Project Management": 129,
    "General Design & Composition": 88,
    "Browsers": 71,
    "General News & Opinion": 66,
    "General Software Development": 42,
    "Marketing": 41,
    "Instant Message": 33,
    "General Communication & Scheduling": 28,
    "General Shopping": 26,
    "Data Modeling & Analysis": 4,
    "Editing & IDEs": 2
  },
  "12": {
    "Email": 4444,
    "Presentation": 3843,
    "Writing": 3114,
    "Meetings": 2078,
    "General Software Development": 1418,
    "Uncategorized": 1228,
    "Project Management": 1204,
    "General Utilities": 634,
    "Instant Message": 404,
    "General Reference & Learning": 309,
    "General Business": 285,
    "Editing & IDEs": 283,
    "Intelligence": 256,
    "Calendars": 244,
    "Professional Networking": 175,
    "Browsers": 152,
    "Search": 117,
    "Systems Operations": 79,
    "General Entertainment": 48,
    "Engineering & Technology": 43,
    "General Communication & Scheduling": 6,
    "General Social Networking": 5,
    "Audio Editing": 1
  },
  "13": {
    "Email": 701,
    "General Reference & Learning": 439,
    "Project Management": 395,
    "Professional Networking": 264,
    "Uncategorized": 71,
    "Intelligence": 38,
    "Browsers": 27,
    "Writing": 26,
    "General Communication & Scheduling": 14,
    "General Utilities": 11,
    "Instant Message": 7,
    "General Business": 5,
    "General Software Development": 4,
    "Presentation": 2
  },
  "14": {
    "Writing": 5302,
    "Email": 5044,
    "General Design & Composition": 2272,
    "Instant Message": 1340,
    "General Software Development": 1026,
    "General Utilities": 927,
    "Accounting": 534,
    "Intelligence": 428,
    "Presentation": 391,
    "Professional Networking": 343,
    "General Business": 315,
    "Search": 153,
    "General Reference & Learning": 143,
    "Project Management": 122,
    "General News & Opinion": 71,
    "General Entertainment": 32,
    "Browsers": 29,
    "Meetings": 14,
    "Calendars": 10,
    "Editing & IDEs": 6,
    "Uncategorized": 2
  },
  "15": {
    "Writing": 2904,
    "Email": 1073,
    "General Reference & Learning": 817,
    "General Design & Composition": 766,
    "Uncategorized": 717,
    "Meetings": 707,
    "Data Modeling & Analysis": 587,
    "Calendars": 442,
    "General Utilities": 417,
    "Search": 381,
    "File Sharing": 373,
    "General Software Development": 363,
    "General Entertainment": 326,
    "Intelligence": 240,
    "Business & Finance": 183,
    "Browsers": 161,
    "Marketing": 114,
    "Accounting": 91,
    "Instant Message": 56,
    "General News & Opinion": 33,
    "Voice Chat": 11,
    "Project Management": 7,
    "General Communication & Scheduling": 4,
    "Travel & Outdoors": 2,
    "Engineering & Technology": 1
  },
  "16": {
    "Writing": 4570,
    "General Reference & Learning": 459,
    "General Software Development": 398,
    "General Utilities": 285,
    "Uncategorized": 208,
    "General Business": 157,
    "Search": 132,
    "Intelligence": 119,
    "General Entertainment": 79,
    "Marketing": 75,
    "Data Modeling & Analysis": 75,
    "Browsers": 66,
    "Email": 57,
    "Project Management": 48,
    "Engineering & Technology": 12,
    "General Design & Composition": 1
  },
  "17": {
    "Writing": 5024,
    "General Reference & Learning": 3232,
    "General Business": 1910,
    "General Utilities": 1054,
    "Intelligence": 726,
    "Presentation": 597,
    "Email": 525,
    "Search": 448,
    "Project Management": 251,
    "Professional Networking": 244,
    "Uncategorized": 239,
    "Calendars": 171,
    "General Entertainment": 110,
    "General News & Opinion": 94,
    "Accounting": 90,
    "Browsers": 66,
    "Marketing": 59,
    "Instant Message": 55,
    "General Software Development": 50,
    "Data Modeling & Analysis": 41,
    "General Shopping": 30,
    "General Communication & Scheduling": 26,
    "Systems Operations": 18,
    "File Sharing": 14,
    "Engineering & Technology": 10
  },
  "18": {
    "Presentation": 7995,
    "Writing": 4062,
    "Meetings": 2667,
    "Email": 1130,
    "General Business": 1043,
    "General Software Development": 618,
    "Search": 497,
    "Uncategorized": 497,
    "General Utilities": 463,
    "Calendars": 323,
    "Intelligence": 312,
    "Browsers": 310,
    "Data Modeling & Analysis": 287,
    "General Reference & Learning": 197,
    "Instant Message": 164,
    "Business & Finance": 153,
    "General Design & Composition": 119,
    "General News & Opinion": 109,
    "Marketing": 85,
    "General Entertainment": 48,
    "General Shopping": 48,
    "General Communication & Scheduling": 25,
    "Internet Utilities": 25,
    "Sports": 25,
    "Science & Technology": 25,
    "Voice Chat": 20,
    "Engineering & Technology": 18,
    "File Sharing": 10,
    "Project Management": 7
  },
  "19": {
    "Writing": 9228,
    "General Software Development": 7362,
    "Email": 3807,
    "Voice Chat": 1528,
    "Uncategorized": 1476,
    "Presentation": 905,
    "General Business": 811,
    "General News & Opinion": 527,
    "Intelligence": 329,
    "Meetings": 324,
    "Professional Networking": 281,
    "Marketing": 257,
    "General Reference & Learning": 253,
    "Project Management": 234,
    "General Design & Composition": 234,
    "Browsers": 228,
    "Search": 208,
    "Calendars": 180,
    "General Utilities": 173,
    "General Entertainment": 62,
    "Instant Message": 50,
    "Engineering & Technology": 40,
    "Science & Technology": 29,
    "Administration": 23,
    "General Communication & Scheduling": 7
  },
  "20": {
    "Email": 4195,
    "Uncategorized": 2712,
    "Writing": 2592,
    "Meetings": 1863,
    "General Business": 1643,
    "General Shopping": 1394,
    "Data Modeling & Analysis": 1195,
    "Search": 1195,
    "Intelligence": 1068,
    "General Design & Composition": 1026,
    "General Entertainment": 1007,
    "Instant Message": 884,
    "Professional Networking": 700,
    "General Software Development": 569,
    "Project Management": 532,
    "Presentation": 335,
    "General Utilities": 274,
    "Browsers": 197,
    "Calendars": 178,
    "General Reference & Learning": 122,
    "Video": 107,
    "Audio Editing": 63,
    "Health & Medicine": 31,
    "Music": 27,
    "Internet Utilities": 22,
    "Comedy": 19,
    "Engineering & Technology": 8,
    "General Communication & Scheduling": 8,
    "General News & Opinion": 8,
    "Maps & Regional": 2
  },
  "21": {
    "Writing": 5341,
    "Email": 3447,
    "General Software Development": 1930,
    "General Shopping": 1872,
    "Meetings": 1222,
    "Presentation": 1080,
    "Instant Message": 935,
    "Calendars": 898,
    "Uncategorized": 879,
    "General Business": 658,
    "General Reference & Learning": 654,
    "Intelligence": 583,
    "Search": 503,
    "General Utilities": 305,
    "Browsers": 114,
    "General Entertainment": 112,
    "Accounting": 112,
    "Employment": 105,
    "Health & Medicine": 89,
    "Engineering & Technology": 87,
    "General Design & Composition": 73,
    "Voice Chat": 55,
    "General News & Opinion": 51,
    "Marketing": 46,
    "Professional Networking": 23,
    "General Communication & Scheduling": 11,
    "Maps & Regional": 8,
    "Project Management": 7
  },
  "22": {
    "Writing": 5842,
    "Email": 2687,
    "Intelligence": 519,
    "General Utilities": 299,
    "General Reference & Learning": 266,
    "Calendars": 259,
    "Instant Message": 205,
    "Uncategorized": 192,
    "Search": 135,
    "General News & Opinion": 72,
    "General Entertainment": 53,
    "Professional Networking": 53,
    "Browsers": 39,
    "Engineering & Technology": 32,
    "Voice Chat": 26,
    "General Software Development": 25,
    "General Communication & Scheduling": 25
  },
  "23": {
    "Professional Networking": 982,
    "General Reference & Learning": 785,
    "General Utilities": 247,
    "Writing": 232,
    "Email": 150,
    "General Software Development": 86,
    "Calendars": 71,
    "Intelligence": 70,
    "Search": 61,
    "Instant Message": 49,
    "Engineering & Technology": 18,
    "Browsers": 16
  },
  "24": {},
  "25": {
    "Writing": 9035,
    "General Design & Composition": 2267,
    "Presentation": 1965,
    "Meetings": 1932,
    "General Utilities": 1921,
    "General Business": 1761,
    "Uncategorized": 907,
    "Health & Medicine": 833,
    "Audio Editing": 753,
    "General Reference & Learning": 641,
    "Search": 393,
    "Email": 388,
    "Calendars": 376,
    "File Sharing": 343,
    "Intelligence": 282,
    "Project Management": 269,
    "Instant Message": 204,
    "Professional Networking": 174,
    "Comedy": 166,
    "General Entertainment": 162,
    "General News & Opinion": 139,
    "Browsers": 92,
    "Sports": 72,
    "General Software Development": 69,
    "Video": 68,
    "Graphic Design": 52,
    "Data Modeling & Analysis": 50,
    "General Shopping": 12,
    "General Communication & Scheduling": 2
  },
  "26": {
    "Writing": 6876,
    "Audio Editing": 2866,
    "General Design & Composition": 2664,
    "General Utilities": 2659,
    "Uncategorized": 2289,
    "General Reference & Learning": 2167,
    "Email": 1054,
    "Video": 694,
    "Meetings": 645,
    "Data Modeling & Analysis": 644,
    "Search": 579,
    "General Entertainment": 497,
    "Calendars": 463,
    "Intelligence": 403,
    "General Shopping": 387,
    "General Business": 333,
    "Legal & Gov't": 281,
    "General News & Opinion": 225,
    "Health & Medicine": 159,
    "Browsers": 153,
    "Electronics": 114,
    "Science & Technology": 97,
    "Marketing": 87,
    "Instant Message": 67,
    "Business & Finance": 55,
    "General Software Development": 43,
    "Engineering & Technology": 42,
    "General Communication & Scheduling": 33,
    "Voice Chat": 32,
    "Project Management": 8,
    "Professional Networking": 8,
    "Music": 6,
    "Systems Operations": 4,
    "Internet Utilities": 4
  },
  "27": {
    "Writing": 4627,
    "Email": 3247,
    "General Design & Composition": 2914,
    "General Business": 1226,
    "Meetings": 947,
    "Project Management": 854,
    "Internet Utilities": 765,
    "General Utilities": 722,
    "Data Modeling & Analysis": 715,
    "General Software Development": 683,
    "Intelligence": 520,
    "Marketing": 452,
    "Instant Message": 450,
    "Professional Networking": 267,
    "Search": 252,
    "Browsers": 227,
    "Calendars": 175,
    "General Entertainment": 128,
    "Engineering & Technology": 62,
    "General News & Opinion": 50,
    "Health & Medicine": 33,
    "General Shopping": 33,
    "Business & Finance": 29,
    "General Reference & Learning": 26,
    "Uncategorized": 12,
    "Science & Technology": 11,
    "General Communication & Scheduling": 7,
    "Audio Editing": 5,
    "Maps & Regional": 1
  },
  "28": {},
  "29": {},
  "30": {}
}