{
  "2022-07-17": {
    "Professional Networking": 630,
    "Writing": 540,
    "General Business": 519,
    "General Utilities": 320,
    "Project Management": 284,
    "Accounting": 270,
    "Instant Message": 224,
    "General News & Opinion": 210,
    "Intelligence": 142,
    "Email": 133,
    "Calendars": 132,
    "Browsers": 132,
    "Sports": 111,
    "General Reference & Learning": 98,
    "General Entertainment": 62,
    "General Software Development": 45,
    "Uncategorized": 33,
    "Data Modeling & Analysis": 26,
    "Audio Editing": 11
  },
  "2022-07-18": {
    "General Software Development": 8365,
    "Email": 2277,
    "General Business": 1640,
    "Uncategorized": 1435,
    "Project Management": 1235,
    "Meetings": 530,
    "Browsers": 474,
    "Calendars": 446,
    "General Reference & Learning": 428,
    "Writing": 346,
    "Search": 316,
    "General News & Opinion": 309,
    "General Utilities": 259,
    "Presentation": 238,
    "Intelligence": 236,
    "Instant Message": 227,
    "Professional Networking": 178,
    "Data Modeling & Analysis": 142,
    "Accounting": 77,
    "General Design & Composition": 42,
    "Internet Utilities": 33,
    "General Entertainment": 22,
    "Engineering & Technology": 20,
    "General Communication & Scheduling": 14,
    "Voice Chat": 12,
    "Business": 8
  },
  "2022-07-19": {},
  "2022-07-20": {},
  "2022-07-21": {},
  "2022-07-22": {},
  "2022-07-23": {}
}