{
  "1": {
    "Software Development": 7702,
    "Communication & Scheduling": 2473,
    "Business": 2072,
    "Design & Composition": 1911,
    "Utilities": 598,
    "Uncategorized": 250,
    "Reference & Learning": 245,
    "Entertainment": 98,
    "News & Opinion": 15
  },
  "2": {
    "Software Development": 8007,
    "Communication & Scheduling": 6588,
    "Design & Composition": 4258,
    "Business": 2816,
    "Uncategorized": 1072,
    "Utilities": 964,
    "Reference & Learning": 393,
    "News & Opinion": 95,
    "Entertainment": 51,
    "Shopping": 11
  },
  "3": {
    "Design & Composition": 9664,
    "Communication & Scheduling": 5939,
    "Business": 1852,
    "Software Development": 1339,
    "Utilities": 803,
    "Uncategorized": 455,
    "Reference & Learning": 317,
    "Social Networking": 273,
    "Entertainment": 86,
    "Shopping": 9
  },
  "4": {
    "Design & Composition": 10730,
    "Communication & Scheduling": 1643,
    "Utilities": 1020,
    "Reference & Learning": 706,
    "Business": 653,
    "Social Networking": 338,
    "Software Development": 231,
    "Entertainment": 208,
    "Uncategorized": 87,
    "News & Opinion": 76,
    "Shopping": 4
  },
  "5": {},
  "6": {},
  "7": {},
  "8": {},
  "9": {},
  "10": {},
  "11": {},
  "12": {},
  "13": {},
  "14": {},
  "15": {},
  "16": {},
  "17": {},
  "18": {},
  "19": {},
  "20": {},
  "21": {},
  "22": {},
  "23": {},
  "24": {},
  "25": {},
  "26": {},
  "27": {}
}