{
  "1": {
    "steps": 10397,
    "total": 305,
    "cal_active": 517,
    "cal_total": 2607,
    "score": 86
  },
  "2": {
    "steps": 11131,
    "total": 419,
    "cal_active": 566,
    "cal_total": 2702,
    "score": 89
  },
  "3": {
    "steps": 11425,
    "total": 467,
    "cal_active": 512,
    "cal_total": 2644,
    "score": 85
  },
  "4": {
    "steps": 11257,
    "total": 389,
    "cal_active": 515,
    "cal_total": 2684,
    "score": 73
  },
  "5": {
    "steps": 12881,
    "total": 408,
    "cal_active": 561,
    "cal_total": 2747,
    "score": 74
  },
  "6": {
    "steps": 8977,
    "total": 371,
    "cal_active": 416,
    "cal_total": 2615,
    "score": 78
  },
  "7": {
    "steps": 10591,
    "total": 391,
    "cal_active": 490,
    "cal_total": 2681,
    "score": 90
  },
  "8": {
    "steps": 11108,
    "total": 535,
    "cal_active": 652,
    "cal_total": 2875,
    "score": 93
  },
  "9": {
    "steps": 13212,
    "total": 419,
    "cal_active": 566,
    "cal_total": 2673,
    "score": 93
  },
  "10": {
    "steps": 9863,
    "total": 421,
    "cal_active": 452,
    "cal_total": 2562,
    "score": 93
  },
  "11": {
    "steps": 13430,
    "total": 352,
    "cal_active": 549,
    "cal_total": 2684,
    "score": 91
  },
  "12": {
    "steps": 9800,
    "total": 221,
    "cal_active": 402,
    "cal_total": 2455,
    "score": 87
  },
  "13": {
    "steps": 9280,
    "total": 347,
    "cal_active": 404,
    "cal_total": 2574,
    "score": 85
  },
  "14": {
    "steps": 10706,
    "total": 375,
    "cal_active": 581,
    "cal_total": 2705,
    "score": 91
  },
  "15": {
    "steps": 9909,
    "total": 562,
    "cal_active": 473,
    "cal_total": 2717,
    "score": 88
  },
  "16": {
    "steps": 15134,
    "total": 568,
    "cal_active": 743,
    "cal_total": 2929,
    "score": 89
  },
  "17": {
    "steps": 7245,
    "total": 279,
    "cal_active": 361,
    "cal_total": 2410,
    "score": 91
  },
  "18": {
    "steps": 7976,
    "total": 320,
    "cal_active": 370,
    "cal_total": 2482,
    "score": 86
  },
  "19": {
    "steps": 12711,
    "total": 397,
    "cal_active": 552,
    "cal_total": 2701,
    "score": 91
  },
  "20": {
    "steps": 13632,
    "total": 341,
    "cal_active": 574,
    "cal_total": 2685,
    "score": 95
  },
  "21": {
    "steps": 12120,
    "total": 505,
    "cal_active": 588,
    "cal_total": 2754,
    "score": 97
  },
  "22": {
    "steps": 8954,
    "total": 445,
    "cal_active": 416,
    "cal_total": 2576,
    "score": 93
  },
  "23": {
    "steps": 15858,
    "total": 486,
    "cal_active": 752,
    "cal_total": 2905,
    "score": 97
  },
  "24": {
    "steps": 15262,
    "total": 411,
    "cal_active": 716,
    "cal_total": 2785,
    "score": 98
  },
  "25": {
    "steps": 11050,
    "total": 429,
    "cal_active": 487,
    "cal_total": 2652,
    "score": 96
  },
  "26": {
    "steps": 543,
    "total": 24,
    "cal_active": 22,
    "cal_total": 1817,
    "score": 92
  },
  "27": {},
  "28": {},
  "29": {}
}