[
  {
    "summary_date": "2021-12-15",
    "period_id": 0,
    "is_longest": 1,
    "timezone": -480,
    "bedtime_end": "2021-12-16T08:15:31-08:00",
    "bedtime_start": "2021-12-15T23:11:31-08:00",
    "breath_average": 14.125,
    "duration": 32640,
    "total": 30240,
    "awake": 2400,
    "rem": 4560,
    "deep": 6030,
    "light": 19650,
    "midpoint_time": 16230,
    "efficiency": 93,
    "restless": 29,
    "onset_latency": 450,
    "hr_5min": [
      0,
      45,
      44,
      45,
      47,
      47,
      48,
      48,
      49,
      50,
      48,
      47,
      45,
      46,
      46,
      45,
      45,
      45,
      43,
      43,
      43,
      44,
      46,
      45,
      46,
      45,
      44,
      44,
      43,
      43,
      44,
      45,
      45,
      45,
      45,
      49,
      43,
      43,
      44,
      41,
      41,
      42,
      42,
      42,
      42,
      43,
      43,
      42,
      42,
      41,
      41,
      40,
      41,
      41,
      41,
      41,
      41,
      40,
      41,
      43,
      43,
      43,
      43,
      43,
      42,
      43,
      44,
      40,
      40,
      40,
      41,
      40,
      42,
      41,
      40,
      40,
      42,
      40,
      41,
      42,
      42,
      42,
      42,
      40,
      40,
      40,
      41,
      39,
      40,
      40,
      40,
      38,
      40,
      42,
      42,
      40,
      41,
      42,
      43,
      42,
      40,
      41,
      42,
      43,
      44,
      43,
      40,
      44,
      47
    ],
    "hr_average": 42.81,
    "hr_lowest": 38,
    "hypnogram_5min": "4222113111222232222222111222222223342222211111112222211133332222221222222222322222222222222233333322222342244",
    "rmssd": 39,
    "rmssd_5min": [
      0,
      34,
      56,
      44,
      20,
      21,
      25,
      21,
      20,
      21,
      38,
      34,
      35,
      21,
      20,
      29,
      55,
      40,
      26,
      35,
      31,
      32,
      27,
      35,
      33,
      20,
      40,
      35,
      45,
      42,
      24,
      22,
      24,
      37,
      19,
      26,
      35,
      34,
      30,
      39,
      30,
      25,
      36,
      31,
      30,
      41,
      38,
      30,
      34,
      33,
      38,
      45,
      45,
      54,
      64,
      37,
      42,
      44,
      48,
      21,
      40,
      45,
      34,
      27,
      42,
      34,
      39,
      43,
      35,
      34,
      30,
      43,
      39,
      46,
      59,
      47,
      49,
      53,
      59,
      30,
      49,
      35,
      42,
      47,
      44,
      51,
      65,
      48,
      48,
      49,
      59,
      70,
      51,
      46,
      35,
      72,
      51,
      37,
      33,
      44,
      58,
      66,
      35,
      33,
      44,
      70,
      72,
      44,
      48
    ],
    "score": 86,
    "score_alignment": 78,
    "score_deep": 97,
    "score_disturbances": 70,
    "score_efficiency": 98,
    "score_latency": 81,
    "score_rem": 68,
    "score_total": 96,
    "temperature_deviation": -0.02,
    "temperature_trend_deviation": 0.11,
    "bedtime_start_delta": -2909,
    "bedtime_end_delta": 29731,
    "midpoint_at_delta": 13321,
    "temperature_delta": -0.02
  }
]