{
  "2022-06-5": {
    "Design & Composition": 2567,
    "Entertainment": 259,
    "Utilities": 67,
    "Business": 33,
    "Reference & Learning": 7
  },
  "2022-06-6": {
    "Software Development": 11208,
    "Business": 5988,
    "Communication & Scheduling": 5667,
    "Design & Composition": 3183,
    "Reference & Learning": 1968,
    "Uncategorized": 1235,
    "Utilities": 877,
    "Entertainment": 724,
    "News & Opinion": 76
  },
  "2022-06-7": {
    "Software Development": 13710,
    "Uncategorized": 2249,
    "Reference & Learning": 1788,
    "Business": 1595,
    "Shopping": 1313,
    "Communication & Scheduling": 1298,
    "Design & Composition": 1280,
    "Utilities": 971,
    "Entertainment": 967,
    "News & Opinion": 730
  },
  "2022-06-8": {
    "Software Development": 9681,
    "Communication & Scheduling": 2561,
    "Business": 2522,
    "Design & Composition": 2298,
    "Utilities": 2067,
    "Entertainment": 988,
    "Uncategorized": 767,
    "Reference & Learning": 567,
    "Social Networking": 201,
    "News & Opinion": 176
  },
  "2022-06-9": {},
  "2022-06-10": {},
  "2022-06-11": {}
}