{
  "2022-01-30": {},
  "2022-01-31": {
    "Design & Composition": 13606,
    "Communication & Scheduling": 8361,
    "Business": 6602,
    "Utilities": 3494,
    "Software Development": 2300,
    "Reference & Learning": 1175,
    "Uncategorized": 571,
    "Entertainment": 231,
    "Social Networking": 123,
    "News & Opinion": 114,
    "Shopping": 3
  },
  "2022-02-1": {
    "Software Development": 5811,
    "Communication & Scheduling": 2075,
    "Design & Composition": 1747,
    "Business": 1724,
    "Utilities": 490,
    "Uncategorized": 201,
    "Reference & Learning": 64,
    "Entertainment": 53,
    "News & Opinion": 3
  },
  "2022-02-2": {},
  "2022-02-3": {},
  "2022-02-4": {},
  "2022-02-5": {}
}