[
  {
    "Rank": 1,
    "Time Spent (seconds)": 4906,
    "Number of People": 1,
    "Category": "Business"
  },
  {
    "Rank": 2,
    "Time Spent (seconds)": 4275,
    "Number of People": 1,
    "Category": "Communication & Scheduling"
  },
  {
    "Rank": 3,
    "Time Spent (seconds)": 4059,
    "Number of People": 1,
    "Category": "Software Development"
  },
  {
    "Rank": 4,
    "Time Spent (seconds)": 1921,
    "Number of People": 1,
    "Category": "Uncategorized"
  },
  {
    "Rank": 5,
    "Time Spent (seconds)": 963,
    "Number of People": 1,
    "Category": "Utilities"
  },
  {
    "Rank": 6,
    "Time Spent (seconds)": 687,
    "Number of People": 1,
    "Category": "Reference & Learning"
  },
  {
    "Rank": 7,
    "Time Spent (seconds)": 502,
    "Number of People": 1,
    "Category": "News & Opinion"
  },
  {
    "Rank": 8,
    "Time Spent (seconds)": 415,
    "Number of People": 1,
    "Category": "Design & Composition"
  },
  {
    "Rank": 9,
    "Time Spent (seconds)": 241,
    "Number of People": 1,
    "Category": "Entertainment"
  },
  {
    "Rank": 10,
    "Time Spent (seconds)": 232,
    "Number of People": 1,
    "Category": "Social Networking"
  }
]