{
  "1": {
    "steps": 12775,
    "total": 320,
    "cal_active": 922,
    "cal_total": 2452,
    "score": 92
  },
  "2": {
    "steps": 3242,
    "total": 170,
    "cal_active": 119,
    "cal_total": 1467,
    "score": 88
  },
  "3": {},
  "4": {},
  "5": {},
  "6": {},
  "7": {},
  "8": {},
  "9": {},
  "10": {},
  "11": {},
  "12": {},
  "13": {},
  "14": {},
  "15": {},
  "16": {},
  "17": {},
  "18": {},
  "19": {},
  "20": {},
  "21": {},
  "22": {},
  "23": {},
  "24": {},
  "25": {},
  "26": {},
  "27": {},
  "28": {},
  "29": {}
}