{
  "2021-10-10": {
    "Writing": 3527,
    "Project Management": 2057,
    "General Business": 1323,
    "Email": 1267,
    "Uncategorized": 782,
    "Audio Editing": 698,
    "General Software Development": 677,
    "General Utilities": 664,
    "Intelligence": 525,
    "Data Modeling & Analysis": 224,
    "Search": 214,
    "Marketing": 182,
    "Browsers": 180,
    "Presentation": 162,
    "General Entertainment": 154,
    "Editing & IDEs": 125,
    "General Reference & Learning": 64,
    "Calendars": 64,
    "General Communication & Scheduling": 60,
    "General News & Opinion": 13,
    "Video": 2,
    "Voice Chat": 1
  },
  "2021-10-11": {
    "Meetings": 2532,
    "Writing": 2158,
    "Uncategorized": 1542,
    "Presentation": 1235,
    "Email": 611,
    "Health & Medicine": 601,
    "General Business": 521,
    "General Utilities": 471,
    "Intelligence": 308,
    "Calendars": 233,
    "General Entertainment": 200,
    "General Reference & Learning": 189,
    "Search": 180,
    "Sports": 170,
    "Project Management": 129,
    "General Design & Composition": 88,
    "Browsers": 71,
    "General News & Opinion": 66,
    "General Software Development": 42,
    "Marketing": 41,
    "Instant Message": 33,
    "General Communication & Scheduling": 28,
    "General Shopping": 26,
    "Data Modeling & Analysis": 4,
    "Editing & IDEs": 2
  },
  "2021-10-12": {
    "Email": 4444,
    "Presentation": 3843,
    "Writing": 3114,
    "Meetings": 2078,
    "General Software Development": 1418,
    "Uncategorized": 1228,
    "Project Management": 1204,
    "General Utilities": 634,
    "Instant Message": 404,
    "General Reference & Learning": 309,
    "General Business": 285,
    "Editing & IDEs": 283,
    "Intelligence": 256,
    "Calendars": 244,
    "Professional Networking": 175,
    "Browsers": 152,
    "Search": 117,
    "Systems Operations": 79,
    "General Entertainment": 48,
    "Engineering & Technology": 43,
    "General Communication & Scheduling": 6,
    "General Social Networking": 5,
    "Audio Editing": 1
  },
  "2021-10-13": {
    "Email": 701,
    "General Reference & Learning": 439,
    "Project Management": 395,
    "Professional Networking": 264,
    "Uncategorized": 71,
    "Intelligence": 38,
    "Browsers": 27,
    "Writing": 26,
    "General Communication & Scheduling": 14,
    "General Utilities": 11,
    "Instant Message": 7,
    "General Business": 5,
    "General Software Development": 4,
    "Presentation": 2
  },
  "2021-10-14": {
    "Writing": 5302,
    "Email": 5044,
    "General Design & Composition": 2272,
    "Instant Message": 1340,
    "General Software Development": 1026,
    "General Utilities": 927,
    "Accounting": 534,
    "Intelligence": 428,
    "Presentation": 391,
    "Professional Networking": 343,
    "General Business": 315,
    "Search": 153,
    "General Reference & Learning": 143,
    "Project Management": 122,
    "General News & Opinion": 71,
    "General Entertainment": 32,
    "Browsers": 29,
    "Meetings": 14,
    "Calendars": 10,
    "Editing & IDEs": 6,
    "Uncategorized": 2
  },
  "2021-10-15": {
    "Writing": 2904,
    "Email": 913,
    "General Reference & Learning": 817,
    "Uncategorized": 768,
    "General Design & Composition": 766,
    "Meetings": 707,
    "Data Modeling & Analysis": 587,
    "Calendars": 442,
    "General Utilities": 417,
    "Search": 381,
    "File Sharing": 373,
    "General Entertainment": 326,
    "General Software Development": 312,
    "Intelligence": 240,
    "Business & Finance": 183,
    "Browsers": 161,
    "Marketing": 114,
    "Accounting": 91,
    "Instant Message": 56,
    "General News & Opinion": 33,
    "Voice Chat": 11,
    "Project Management": 7,
    "General Communication & Scheduling": 4,
    "Travel & Outdoors": 2,
    "Engineering & Technology": 1
  },
  "2021-10-16": {}
}