{
  "2021-11-21": {
    "Writing": 5631,
    "Audio Editing": 1931,
    "General Business": 1263,
    "General Entertainment": 909,
    "General Software Development": 863,
    "General Utilities": 727,
    "Intelligence": 646,
    "General Reference & Learning": 497,
    "Project Management": 182,
    "Editing & IDEs": 157,
    "Browsers": 149,
    "Data Modeling & Analysis": 120,
    "Search": 52,
    "Internet Utilities": 30
  },
  "2021-11-22": {
    "Project Management": 4064,
    "Writing": 2391,
    "General Software Development": 1782,
    "Uncategorized": 1435,
    "Email": 1112,
    "General Business": 953,
    "General News & Opinion": 852,
    "General Reference & Learning": 808,
    "Calendars": 804,
    "General Utilities": 490,
    "Meetings": 483,
    "Travel & Outdoors": 479,
    "Intelligence": 478,
    "Marketing": 432,
    "Data Modeling & Analysis": 410,
    "Presentation": 339,
    "Browsers": 269,
    "Professional Networking": 258,
    "Search": 249,
    "Accounting": 206,
    "General Communication & Scheduling": 180,
    "Sports": 134,
    "Instant Message": 132,
    "Internet Utilities": 131,
    "General Entertainment": 126,
    "General Design & Composition": 111,
    "Systems Operations": 64,
    "Editing & IDEs": 47,
    "Science & Technology": 37,
    "File Sharing": 34,
    "Engineering & Technology": 30,
    "Business": 21,
    "Health & Medicine": 8
  },
  "2021-11-23": {
    "General Software Development": 4098,
    "Data Modeling & Analysis": 2322,
    "Writing": 2180,
    "Audio Editing": 1996,
    "Editing & IDEs": 1402,
    "Project Management": 1235,
    "General Utilities": 1147,
    "Instant Message": 1013,
    "Email": 943,
    "Intelligence": 928,
    "Meetings": 657,
    "Calendars": 649,
    "Uncategorized": 563,
    "Video": 368,
    "Browsers": 281,
    "Search": 252,
    "General Reference & Learning": 193,
    "General News & Opinion": 189,
    "Presentation": 134,
    "Sports": 125,
    "General Entertainment": 78,
    "General Shopping": 65,
    "General Business": 36,
    "General Communication & Scheduling": 8,
    "Engineering & Technology": 7,
    "Marketing": 3,
    "Accounting": 2,
    "Systems Operations": 2
  },
  "2021-11-24": {
    "General Software Development": 12475,
    "Uncategorized": 4315,
    "Editing & IDEs": 3141,
    "General Utilities": 2645,
    "Data Modeling & Analysis": 1887,
    "Writing": 1812,
    "Project Management": 1462,
    "Email": 1095,
    "Browsers": 965,
    "Intelligence": 942,
    "Search": 696,
    "Meetings": 673,
    "Calendars": 621,
    "General Reference & Learning": 566,
    "Quality Assurance": 528,
    "Engineering & Technology": 347,
    "Systems Operations": 208,
    "General Business": 183,
    "General Entertainment": 119,
    "General Design & Composition": 99,
    "Instant Message": 61,
    "General News & Opinion": 30,
    "Sports": 27,
    "Video": 19,
    "File Sharing": 17,
    "General Shopping": 13,
    "General Communication & Scheduling": 7,
    "Photos": 5,
    "Voice Chat": 2,
    "Marketing": 1
  },
  "2021-11-25": {
    "Audio Editing": 2436,
    "Editing & IDEs": 1232,
    "General Software Development": 1078,
    "Quality Assurance": 660,
    "Writing": 563,
    "Intelligence": 463,
    "Project Management": 436,
    "General Utilities": 402,
    "Instant Message": 306,
    "General Entertainment": 129,
    "Calendars": 126,
    "Engineering & Technology": 117,
    "Email": 66,
    "Browsers": 52,
    "Uncategorized": 50,
    "Search": 43,
    "General Reference & Learning": 19,
    "General News & Opinion": 18
  },
  "2021-11-26": {},
  "2021-11-27": {}
}