{
  "2021-12-19": {
    "Writing": 3017,
    "Audio Editing": 985,
    "Internet Utilities": 941,
    "General Entertainment": 716,
    "General Utilities": 654,
    "Intelligence": 397,
    "Uncategorized": 395,
    "Search": 282,
    "Project Management": 243,
    "General Software Development": 196,
    "General Business": 190,
    "Instant Message": 188,
    "Calendars": 142,
    "General Reference & Learning": 140,
    "Browsers": 137,
    "General Shopping": 94,
    "Health & Medicine": 61,
    "Email": 58,
    "Presentation": 15,
    "Engineering & Technology": 14,
    "General News & Opinion": 2
  },
  "2021-12-20": {
    "Marketing": 3305,
    "General Software Development": 2520,
    "Writing": 2430,
    "Email": 1809,
    "Meetings": 1791,
    "Uncategorized": 1556,
    "Presentation": 1162,
    "General Business": 838,
    "Travel & Outdoors": 832,
    "Browsers": 628,
    "General Reference & Learning": 617,
    "Search": 548,
    "Health & Medicine": 492,
    "General Utilities": 377,
    "Quality Assurance": 345,
    "Intelligence": 305,
    "Internet Utilities": 228,
    "Business & Finance": 215,
    "Data Modeling & Analysis": 212,
    "General Design & Composition": 203,
    "Project Management": 186,
    "General Social Networking": 177,
    "General Entertainment": 160,
    "General Shopping": 73,
    "Calendars": 55,
    "General News & Opinion": 45,
    "Video": 29,
    "Instant Message": 17,
    "General Communication & Scheduling": 11,
    "Engineering & Technology": 10,
    "Audio Editing": 2,
    "Accounting": 2
  },
  "2021-12-21": {
    "Data Modeling & Analysis": 2769,
    "Email": 1822,
    "Writing": 1800,
    "Marketing": 1733,
    "Uncategorized": 1643,
    "General Software Development": 1496,
    "Presentation": 1407,
    "General Business": 838,
    "Search": 444,
    "Intelligence": 367,
    "Browsers": 342,
    "Instant Message": 270,
    "General Utilities": 224,
    "General News & Opinion": 172,
    "Accounting": 137,
    "Calendars": 49,
    "General Entertainment": 46,
    "Project Management": 44,
    "General Reference & Learning": 22,
    "Internet Utilities": 14
  },
  "2021-12-22": {},
  "2021-12-23": {},
  "2021-12-24": {},
  "2021-12-25": {}
}