[
  {
    "summary_date": "2021-07-12",
    "period_id": 1,
    "is_longest": 1,
    "timezone": -420,
    "bedtime_end": "2021-07-13T08:00:33-07:00",
    "bedtime_start": "2021-07-12T23:05:33-07:00",
    "breath_average": 13.75,
    "duration": 32100,
    "total": 28020,
    "awake": 4080,
    "rem": 5430,
    "deep": 3510,
    "light": 19080,
    "midpoint_time": 16200,
    "efficiency": 87,
    "restless": 36,
    "onset_latency": 1320,
    "hr_5min": [
      0,
      57,
      57,
      58,
      57,
      55,
      55,
      53,
      51,
      51,
      51,
      51,
      54,
      55,
      57,
      54,
      54,
      52,
      51,
      49,
      49,
      49,
      50,
      50,
      53,
      54,
      54,
      53,
      50,
      49,
      47,
      47,
      47,
      50,
      49,
      48,
      47,
      47,
      46,
      46,
      46,
      46,
      48,
      49,
      48,
      48,
      49,
      49,
      46,
      44,
      44,
      43,
      44,
      45,
      46,
      46,
      44,
      43,
      43,
      43,
      43,
      45,
      47,
      44,
      43,
      42,
      43,
      43,
      43,
      43,
      45,
      45,
      45,
      44,
      43,
      43,
      43,
      43,
      43,
      43,
      41,
      42,
      43,
      44,
      44,
      42,
      43,
      45,
      47,
      45,
      45,
      45,
      44,
      44,
      43,
      44,
      0,
      0,
      0,
      0,
      47,
      48,
      47,
      48,
      47,
      48,
      48,
      0
    ],
    "hypnogram_5min": "42442112222433443322112221142222222222222221221222222222221122322222232222222112223322233223233343333244434",
    "rmssd": 43,
    "rmssd_5min": [
      0,
      12,
      14,
      17,
      11,
      12,
      15,
      29,
      47,
      37,
      56,
      22,
      16,
      14,
      22,
      18,
      16,
      19,
      28,
      24,
      20,
      17,
      31,
      35,
      17,
      13,
      14,
      20,
      23,
      26,
      66,
      40,
      47,
      26,
      59,
      27,
      40,
      41,
      41,
      45,
      64,
      173,
      22,
      24,
      28,
      21,
      18,
      22,
      59,
      73,
      55,
      53,
      58,
      37,
      31,
      28,
      48,
      47,
      52,
      45,
      59,
      52,
      35,
      42,
      66,
      64,
      44,
      41,
      41,
      78,
      37,
      36,
      31,
      40,
      35,
      35,
      37,
      45,
      40,
      56,
      66,
      107,
      54,
      89,
      63,
      74,
      72,
      31,
      41,
      44,
      47,
      32,
      61,
      59,
      90,
      57,
      0,
      0,
      0,
      0,
      56,
      44,
      35,
      33,
      29,
      35,
      36,
      0
    ],
    "score": 82,
    "score_alignment": 81,
    "score_deep": 68,
    "score_disturbances": 73,
    "score_efficiency": 88,
    "score_latency": 81,
    "score_rem": 80,
    "score_total": 88,
    "temperature_deviation": 0.23,
    "temperature_trend_deviation": 0.42,
    "bedtime_start_delta": -3267,
    "bedtime_end_delta": 28833,
    "midpoint_at_delta": 12933,
    "temperature_delta": 0.23,
    "hr_lowest": 41,
    "hr_average": 47.33
  }
]