{
  "1": {},
  "2": {},
  "3": {},
  "4": {},
  "5": {},
  "6": {
    "total": 47250,
    "rem": 6630,
    "awake": 10350,
    "deep": 9960,
    "duration": 57600,
    "efficiency": 166,
    "light": 30660,
    "score": 145
  },
  "7": {
    "total": 788220,
    "rem": 152640,
    "awake": 96480,
    "deep": 141570,
    "duration": 884700,
    "efficiency": 2585,
    "light": 494010,
    "score": 2267
  },
  "8": {
    "total": 670020,
    "rem": 135570,
    "awake": 67620,
    "deep": 125550,
    "duration": 737640,
    "efficiency": 2270,
    "light": 408900,
    "score": 1976
  },
  "9": {
    "total": 32430,
    "rem": 7440,
    "awake": 3990,
    "deep": 4140,
    "duration": 36420,
    "efficiency": 89,
    "light": 20850,
    "score": 88
  },
  "10": {},
  "11": {},
  "12": {}
}