[
  {
    "summary_date": "2021-12-10",
    "period_id": 1,
    "is_longest": 1,
    "timezone": -480,
    "bedtime_end": "2021-12-11T09:26:29-08:00",
    "bedtime_start": "2021-12-10T23:02:29-08:00",
    "breath_average": 13.625,
    "duration": 37440,
    "total": 24000,
    "awake": 13440,
    "rem": 5040,
    "deep": 2910,
    "light": 16050,
    "midpoint_time": 23640,
    "efficiency": 64,
    "restless": 34,
    "onset_latency": 7650,
    "hr_5min": [
      0,
      0,
      0,
      0,
      0,
      0,
      0,
      0,
      0,
      0,
      0,
      0,
      0,
      0,
      0,
      0,
      0,
      0,
      0,
      0,
      0,
      0,
      0,
      0,
      0,
      0,
      0,
      0,
      0,
      0,
      0,
      0,
      44,
      43,
      0,
      0,
      0,
      0,
      42,
      43,
      42,
      43,
      43,
      43,
      44,
      44,
      44,
      44,
      45,
      45,
      45,
      45,
      44,
      43,
      43,
      42,
      41,
      41,
      41,
      42,
      42,
      42,
      43,
      44,
      41,
      42,
      39,
      0,
      0,
      0,
      0,
      0,
      0,
      39,
      39,
      40,
      39,
      43,
      0,
      0,
      41,
      40,
      39,
      39,
      0,
      40,
      43,
      42,
      43,
      43,
      43,
      42,
      43,
      43,
      43,
      42,
      46,
      46,
      0,
      40,
      41,
      40,
      41,
      0,
      0,
      0,
      0,
      43,
      43,
      43,
      42,
      43,
      42,
      43,
      41,
      0,
      44,
      45,
      44,
      47,
      48,
      47,
      47,
      47,
      48
    ],
    "hr_average": 42.78,
    "hr_lowest": 39,
    "hypnogram_5min": "44444444444444444444444444444444233444222213222222332222221111122244334442224443222222222222222233322221112222222222222333344",
    "rmssd": 50,
    "rmssd_5min": [
      0,
      0,
      0,
      0,
      0,
      0,
      0,
      0,
      0,
      0,
      0,
      0,
      0,
      0,
      0,
      0,
      0,
      0,
      0,
      0,
      0,
      0,
      0,
      0,
      0,
      0,
      0,
      0,
      0,
      0,
      0,
      0,
      32,
      38,
      0,
      0,
      0,
      0,
      56,
      51,
      51,
      58,
      36,
      111,
      75,
      53,
      40,
      33,
      23,
      31,
      32,
      36,
      50,
      53,
      44,
      60,
      77,
      65,
      58,
      47,
      57,
      51,
      51,
      53,
      41,
      32,
      62,
      0,
      0,
      0,
      0,
      0,
      0,
      71,
      47,
      67,
      50,
      53,
      0,
      0,
      91,
      72,
      68,
      69,
      0,
      59,
      44,
      46,
      35,
      23,
      34,
      52,
      41,
      31,
      50,
      44,
      31,
      36,
      0,
      62,
      58,
      50,
      64,
      0,
      0,
      0,
      0,
      58,
      42,
      56,
      54,
      53,
      78,
      79,
      68,
      0,
      60,
      69,
      38,
      30,
      29,
      19,
      35,
      51,
      43
    ],
    "score": 55,
    "score_alignment": 23,
    "score_deep": 58,
    "score_disturbances": 72,
    "score_efficiency": 34,
    "score_latency": 1,
    "score_rem": 75,
    "score_total": 72,
    "temperature_deviation": -0.16,
    "temperature_trend_deviation": 0.4,
    "bedtime_start_delta": -3451,
    "bedtime_end_delta": 33989,
    "midpoint_at_delta": 20189,
    "temperature_delta": -0.16
  }
]