{
  "2021-08-22": {
    "total": 24000,
    "rem": 6570,
    "awake": 2880,
    "deep": 4770,
    "duration": 26880,
    "efficiency": 89,
    "light": 12660,
    "score": 78
  },
  "2021-08-23": {
    "total": 28350,
    "rem": 5400,
    "awake": 1290,
    "deep": 6750,
    "duration": 29640,
    "efficiency": 96,
    "light": 16200,
    "score": 86
  },
  "2021-08-24": {},
  "2021-08-25": {},
  "2021-08-26": {
    "total": 35040,
    "rem": 7620,
    "awake": 4260,
    "deep": 2880,
    "duration": 39300,
    "efficiency": 89,
    "light": 24540,
    "score": 86
  },
  "2021-08-27": {
    "total": 30240,
    "rem": 5340,
    "awake": 2520,
    "deep": 4350,
    "duration": 32760,
    "efficiency": 92,
    "light": 20550,
    "score": 81
  },
  "2021-08-28": {
    "total": 29130,
    "rem": 4170,
    "awake": 2430,
    "deep": 6000,
    "duration": 31560,
    "efficiency": 92,
    "light": 18960,
    "score": 81
  }
}