{
  "2021": {
    "Design & Composition": 895487,
    "Business": 315816,
    "Communication & Scheduling": 468399,
    "News & Opinion": 48615,
    "Software Development": 405380,
    "Utilities": 123171,
    "Entertainment": 67769,
    "Reference & Learning": 151159,
    "Shopping": 19490,
    "Uncategorized": 117896,
    "Social Networking": 17959
  },
  "2022": {
    "Design & Composition": 907360,
    "Business": 430310,
    "Entertainment": 52137,
    "Communication & Scheduling": 389847,
    "Utilities": 107651,
    "Software Development": 391155,
    "Reference & Learning": 84011,
    "News & Opinion": 32383,
    "Uncategorized": 107664,
    "Social Networking": 16411,
    "Shopping": 8445
  }
}