{
  "2021": {
    "Design & Composition": 895487,
    "Business": 315816,
    "Communication & Scheduling": 468399,
    "News & Opinion": 48615,
    "Software Development": 405380,
    "Utilities": 123171,
    "Entertainment": 67769,
    "Reference & Learning": 151159,
    "Shopping": 19490,
    "Uncategorized": 117896,
    "Social Networking": 17959
  },
  "2022": {
    "Design & Composition": 384131,
    "Business": 155409,
    "Entertainment": 23325,
    "Communication & Scheduling": 173158,
    "Utilities": 44287,
    "Software Development": 107393,
    "Reference & Learning": 37858,
    "News & Opinion": 12016,
    "Uncategorized": 33945,
    "Social Networking": 6108,
    "Shopping": 2420
  }
}